{
	"visual":[
		"-webkit-appearance",
		"-webkit-filter",
		"-webkit-perspective",
		"-webkit-perspective-origin",
		"-webkit-print-color-adjust",
		"-webkit-transform",
		"-webkit-transform-origin",
		"-webkit-transform-origin-x",
		"-webkit-transform-origin-y",
		"-webkit-transform-origin-z",
		"-webkit-transform-style",
		"-webkit-transition-delay",
		"-webkit-transition-duration",
		"-webkit-transition-property",
		"-webkit-transition-timing-function",
		"-webkit-backface-visibility",
		"-webkit-animation",
		"-webkit-animation-delay",
		"-webkit-animation-direction",
		"-webkit-animation-duration",
		"-webkit-animation-fill-mode",
		"-webkit-animation-iteration-count",
		"-webkit-animation-name",
		"-webkit-animation-play-state",
		"-webkit-animation-timing-function"],
	"box":["-webkit-box-align",
		"-webkit-box-decoration-break",
		"-webkit-box-direction",
		"-webkit-box-flex",
		"-webkit-box-flex-group",
		"-webkit-box-lines",
		"-webkit-box-ordinal-group",
		"-webkit-box-orient",
		"-webkit-box-pack",
		"-webkit-box-reflect",
		"-webkit-box-shadow",
		"-webkit-box-sizing"],
	"column": [
		"-webkit-column-break-after",
		"-webkit-column-break-before",
		"-webkit-column-break-inside",
		"-webkit-column-count",
		"-webkit-column-gap",
		"-webkit-column-progression",
		"-webkit-column-rule",
		"-webkit-column-rule-color",
		"-webkit-column-rule-style",
		"-webkit-column-rule-width",
		"-webkit-column-width"],
	"margin": [
		"-webkit-margin-bottom-collapse",
		"-webkit-margin-collapse",
		"-webkit-margin-start",
		"-webkit-margin-top-collapse"],
	"marquee": [
		"-webkit-marquee",
		"-webkit-marquee-direction",
		"-webkit-marquee-increment",
		"-webkit-marquee-repetition",
		"-webkit-marquee-speed",
		"-webkit-marquee-style"],
	"background": [
		"-webkit-background-clip",
		"-webkit-background-origin",
		"-webkit-background-size"],
	"flex": [
		"-webkit-flex",
		"-webkit-flex-basis",
		"-webkit-flex-direction",
		"-webkit-flex-grow",
		"-webkit-flex-shrink",
		"-webkit-flex-wrap",
		"-webkit-align-content",
		"-webkit-align-items",
		"-webkit-align-self",
		"-webkit-justify-content"],
	"mask": [
		"-webkit-mask-box-image",
		"-webkit-mask-clip",
		"-webkit-mask-composite",
		"-webkit-mask-image",
		"-webkit-mask-origin",
		"-webkit-mask-position",
		"-webkit-mask-position-x",
		"-webkit-mask-position-y",
		"-webkit-mask-repeat",
		"-webkit-mask-size"],
	"text": [
		"-webkit-line-break",
		"-webkit-nbsp-mode",
		"-webkit-rtl-ordering",
		"-webkit-text-size-adjust",
		"-webkit-text-fill-color",
		"-webkit-text-security",
		"-webkit-text-emphasis",
		"-webkit-text-emphasis-style",
		"-webkit-text-stroke",
		"-webkit-tap-highlight-color",
		"-webkit-writing-mode"],
	"font": [
		"-webkit-font-kerning",
		"-webkit-font-smoothing",
		"-webkit-font-variant-ligatures"],
		"userInteraction": [
		"-webkit-user-drag",
		"-webkit-user-modify",
		"-webkit-user-select"],
	"wrap": [
		"-webkit-wrap-flow",
		"-webkit-wrap-margin",
		"-webkit-wrap-padding",
		"-webkit-wrap-through"],
	"flow": [
		"-webkit-flow-from",
		"-webkit-flow-into"],
	"padding":[
		"-webkit-padding-start"],
	"border": [
		"-webkit-border-image",
		"-webkit-border-radius"
	],
	"types": [
		"visual",
		"box",
		"column",
		"margin",
		"marquee",
		"background",
		"flex",
		"mask",
		"text",
		"font",
		"wrap",
		"flow",
		"padding",
		"border"
	]
}